towel/__init__.py
towel/base.py
towel/brain/__init__.py
towel/brain/base.py
towel/brain/claude.py
towel/brain/ollama.py
towel/brain/tools/__init__.py
towel/brain/tools/fun.py
towel/brain/tools/prompt/__init__.py
towel/brain/tools/prompt/generic.py
towel/brain/tools/prompt/mistral.py
towel/guide.py
towel/prompt/__init__.py
towel/prompt/plan.py
towel/thinker.py
towel/toolbox/__init__.py
towel/toolbox/web.py
towel/tools.py
towel/type/__init__.py
towel/type/plan.py
towel.py
42towels-0.1.1011.dist-info/METADATA
42towels-0.1.1011.dist-info/WHEEL
42towels-0.1.1011.dist-info/entry_points.txt
42towels-0.1.1011.dist-info/RECORD
