Metadata-Version: 2.1
Name: 42towels
Version: 0.1.1011
Summary: an essential item for any intergalactic hitchhiker
License: MIT
Keywords: ai,agents,llm,function calling,planning,api,code generation
Author: tolitius
Requires-Python: >=3.9,<4.0
Classifier: License :: OSI Approved :: MIT License
Classifier: Programming Language :: Python :: 3
Classifier: Programming Language :: Python :: 3.9
Classifier: Programming Language :: Python :: 3.10
Classifier: Programming Language :: Python :: 3.11
Classifier: Programming Language :: Python :: 3.12
Requires-Dist: PyMuPDF (==1.24.4)
Requires-Dist: anthropic (==0.28.1)
Requires-Dist: beautifulsoup4 (==4.12.3)
Requires-Dist: colalamo (==0.1.2106)
Requires-Dist: duckduckgo-search (==6.1.1)
Requires-Dist: googlesearch-python (==1.2.4)
Requires-Dist: instructor (==1.3.4)
Requires-Dist: ollama (==0.2.1)
Requires-Dist: openai (==1.35.1)
Requires-Dist: pyreadline3 (==3.4.1) ; os_name == "nt"
Requires-Dist: python-dotenv (==1.0.1)
Requires-Dist: replicate (==0.26.0)
Project-URL: documentation, https://github.com/tolitius/towel?tab=readme-ov-file#-towel
Project-URL: homepage, https://github.com/tolitius/towel
Project-URL: issues, https://github.com/tolitius/towel/issues
Project-URL: repository, https://github.com/tolitius/towel
